faster_whisper/__init__.py
faster_whisper/audio.py
faster_whisper/feature_extractor.py
faster_whisper/tokenizer.py
faster_whisper/transcribe.py
faster_whisper/utils.py
faster_whisper/vad.py
faster_whisper/version.py
faster_whisper/assets/__init__.py
faster_whisper/assets/pyannote_vad_model.bin
faster_whisper/assets/silero_vad.onnx
topai_faster_whisper-1.0.4.post4.dist-info/LICENSE
topai_faster_whisper-1.0.4.post4.dist-info/METADATA
topai_faster_whisper-1.0.4.post4.dist-info/WHEEL
topai_faster_whisper-1.0.4.post4.dist-info/top_level.txt
topai_faster_whisper-1.0.4.post4.dist-info/RECORD
